brain_slam-0.0.11.dist-info/licenses/LICENSE
slam/__init__.py
slam/_version.py
slam/curvature.py
slam/differential_geometry.py
slam/distortion.py
slam/generate_parametric_surfaces.py
slam/geodesics.py
slam/io.py
slam/mapping.py
slam/remeshing.py
slam/spangy.py
slam/sulcal_depth.py
slam/sulcal_graph.py
slam/surface_profiling.py
slam/texture.py
slam/topology.py
slam/utils.py
slam/vertex_voronoi.py
slam/watershed.py
tests/__init__.py
tests/test_curvature.py
tests/test_differential_geometry.py
tests/test_distortion.py
tests/test_generate_parametric_surfaces.py
tests/test_geodesics.py
tests/test_io.py
tests/test_spangy.py
tests/test_sulcal_depth.py
tests/test_sulcal_graph.py
tests/test_surface_profiling.py
tests/test_texture.py
tests/test_vertex_voronoi.py
tests/test_watershed.py
brain_slam-0.0.11.dist-info/METADATA
brain_slam-0.0.11.dist-info/WHEEL
brain_slam-0.0.11.dist-info/top_level.txt
brain_slam-0.0.11.dist-info/RECORD
