Metadata-Version: 2.4
Name: brain-slam
Version: 0.0.11
Summary: Surface anaLysis And Modeling
Home-page: https://github.com/brain-slam/slam
Author: Guillaume Auzias
License: MIT
Classifier: Programming Language :: Python :: 3
Classifier: License :: OSI Approved :: MIT License
Classifier: Operating System :: Unix
Classifier: Operating System :: MacOS :: MacOS X
Requires-Python: >=3.12
License-File: LICENSE
Requires-Dist: numpy
Requires-Dist: scipy
Requires-Dist: trimesh
Requires-Dist: nibabel
Requires-Dist: networkx
Provides-Extra: full
Requires-Dist: tvb-gdist; extra == "full"
Requires-Dist: rtree; extra == "full"
Requires-Dist: shapely; extra == "full"
Provides-Extra: dev
Requires-Dist: tvb-gdist; extra == "dev"
Requires-Dist: flake8; extra == "dev"
Requires-Dist: autopep8; extra == "dev"
Requires-Dist: pytest; extra == "dev"
Requires-Dist: pytest-cov; extra == "dev"
Requires-Dist: coveralls; extra == "dev"
Requires-Dist: rtree; extra == "dev"
Requires-Dist: shapely; extra == "dev"
Provides-Extra: doc
Requires-Dist: tvb-gdist; extra == "doc"
Requires-Dist: flake8; extra == "doc"
Requires-Dist: autopep8; extra == "doc"
Requires-Dist: pytest; extra == "doc"
Requires-Dist: pytest-cov; extra == "doc"
Requires-Dist: coveralls; extra == "doc"
Requires-Dist: rtree; extra == "doc"
Requires-Dist: shapely; extra == "doc"
Requires-Dist: sphinx; extra == "doc"
Requires-Dist: sphinx-gallery; extra == "doc"
Requires-Dist: sphinx_bootstrap_theme; extra == "doc"
Requires-Dist: numpydoc; extra == "doc"
Requires-Dist: six; extra == "doc"
Requires-Dist: python-dateutil; extra == "doc"
Requires-Dist: sphinxcontrib-fulltoc; extra == "doc"
Requires-Dist: matplotlib; extra == "doc"
Dynamic: author
Dynamic: classifier
Dynamic: description
Dynamic: description-content-type
Dynamic: home-page
Dynamic: license
Dynamic: license-file
Dynamic: provides-extra
Dynamic: requires-dist
Dynamic: requires-python
Dynamic: summary
